blocksWorld/__init__.py
blocksWorld/draw.py
blocksWorld/polygon.py
blocksWorld/transform.py
blocksWorld-0.0.8.dist-info/DESCRIPTION.rst
blocksWorld-0.0.8.dist-info/LICENSE.txt
blocksWorld-0.0.8.dist-info/METADATA
blocksWorld-0.0.8.dist-info/RECORD
blocksWorld-0.0.8.dist-info/WHEEL
blocksWorld-0.0.8.dist-info/metadata.json
blocksWorld-0.0.8.dist-info/top_level.txt
