Metadata-Version: 2.0
Name: blocksWorld
Version: 0.0.8
Summary: BlocksWorld is a tool for generating simple test images.
Home-page: https://github.com/takanokage/blocksWorld
Author: Dan Petre
Author-email: danut.petre@gmail.com
License: MIT
Keywords: blocks world
Platform: UNKNOWN
Classifier: Development Status :: 3 - Alpha
Classifier: Environment :: X11 Applications
Classifier: Intended Audience :: Education
Classifier: Intended Audience :: Other Audience
Classifier: Intended Audience :: Science/Research
Classifier: License :: OSI Approved :: MIT License
Classifier: Natural Language :: English
Classifier: Operating System :: POSIX :: Linux
Classifier: Operating System :: MacOS
Classifier: Programming Language :: Python :: 3
Classifier: Programming Language :: Python :: 3.5
Classifier: Topic :: Education
Classifier: Topic :: Scientific/Engineering
Classifier: Topic :: Scientific/Engineering :: Mathematics
Classifier: Topic :: Software Development :: Libraries :: Python Modules
Classifier: Topic :: Utilities
Requires-Dist: numpy
Requires-Dist: pillow (>=6.0.0)
Requires-Dist: recordtype
